sugarloaf_utilities/__init__.py
sugarloaf_utilities/components.py
sugarloaf_utilities/debug.py
sugarloaf_utilities/deployment.py
sugarloaf_utilities/io.py
sugarloaf_utilities/main.py
sugarloaf_utilities/secrets.py
sugarloaf_utilities/template.py
sugarloaf_utilities/terraform.py
sugarloaf_utilities/tests/__init__.py
sugarloaf_utilities/tests/test_deployment.py
sugarloaf_utilities/tests/test_template.py
sugarloaf_utilities/tests/test_terraform.py
sugarloaf_utilities-0.1.2.dist-info/entry_points.txt
sugarloaf_utilities-0.1.2.dist-info/WHEEL
sugarloaf_utilities-0.1.2.dist-info/METADATA
sugarloaf_utilities-0.1.2.dist-info/RECORD
