Metadata-Version: 2.1
Name: sugarloaf-utilities
Version: 0.1.2
Summary: 
License: MIT
Author: Pierce Freeman
Author-email: pierce@freeman.vc
Requires-Python: >=3.10,<4.0
Classifier: License :: OSI Approved :: MIT License
Classifier: Programming Language :: Python :: 3
Classifier: Programming Language :: Python :: 3.10
Requires-Dist: click (>=7.0,<8.0)
Requires-Dist: kubernetes (>=24.2.0,<25.0.0)
Requires-Dist: rich (>=12.5.0,<13.0.0)
